pleth/__init__.py
pleth/abi.py
pleth/config.py
pleth/core.py
pleth/denomination.py
pleth/ecdsa.py
pleth/objectdict.py
pleth/rate.py
pleth/rlp.py
pleth/rpc.py
pleth/secp256k1.py
pleth/wallet.py
pleth-1.2.1.dist-info/METADATA
pleth-1.2.1.dist-info/WHEEL
pleth-1.2.1.dist-info/licenses/LICENSE
pleth-1.2.1.dist-info/RECORD
