Metadata-Version: 2.4
Name: pleth
Version: 1.2.1
Summary: Pleth: Ethereum Library For Humans
Project-URL: homepage, https://github.com/mohanson/pleth
Author-email: Mohanson <mohanson@outlook.com>
License: MIT License
License-File: LICENSE
Requires-Dist: pycryptodome
Requires-Dist: requests
